pargp/__init__.py
pargp/_args.py
pargp/_parser.py
pydanticargparser-0.1.0.dist-info/METADATA
pydanticargparser-0.1.0.dist-info/WHEEL
pydanticargparser-0.1.0.dist-info/licenses/LICENSE
pydanticargparser-0.1.0.dist-info/RECORD
