Metadata-Version: 2.4
Name: pydanticargparser
Version: 0.1.0
Summary: Argparse integration with Pydantic models.
Project-URL: Homepage, https://github.com/yaHzm/pydanticargparser
Project-URL: Repository, https://github.com/yaHzm/pydanticargparser
Author-email: Yannik Heizmann <github@yannikheizmann.com>
License: MIT License
License-File: LICENSE
Requires-Python: >=3.9
Requires-Dist: argparse>=1.4.0
Requires-Dist: pydantic>=2.0
